Workbook

Sheet 01 Project Info
A1: STANDARD COSTING & VARIANCE ANALYSIS Illustrative Automobile Manufacturing Case Study
A4: Company Context | B4: Maruti Suzuki India Limited
A5: Industry | B5: Automobile Manufacturing
A6: Analysis Period | B6: FY 2025–26
A7: Model Type | B7: Illustrative Standard Costing Model
A8: Production Batch | B8: 1,000 vehicles
A9: Primary Tool | B9: Microsoft Excel
A10: Analysis Areas | B10: Material, Labour & Variable Overhead
A12: Project Objective
A13: To develop an illustrative standard-costing model for a compact passenger-vehicle manufacturing environment and analyse material, labour and overhead variances.
A15: Important Data Note
A16: Publicly available Maruti Suzuki information is used for company and industry context. Detailed standard and actual cost figures are illustrative assumptions developed for educational and portfolio modelling purposes and do not represent Maruti Suzuki's confidential internal cost data.
A18: Prepared By | B18: Nilankshi Yadav
A19: Project Type | B19: Finance & Cost Accounting Portfolio Project
A21: KEY MODEL OUTPUTS | B21: Amount
A22: Standard Cost | B22: 133875000
A23: Actual Cost | B23: 137140000
A24: Overall Cost Variance | B24: ₹ 32,65,000 Adverse
A25: Variance per Vehicle | B25: ₹ 3,265 Adverse

Sheet 02 Assumption & Sources
A1: Category | B1: Variable | C1: Standard / Base Value | D1: Actual Value | E1: Unit | F1: Data Classification | G1: Basis / Source | H1: Notes
A2: Production | B2: Production batch | C2: 1000 | D2: 1000 | E2: Vehicles | F2: Modelling assumption | G2: Portfolio modelling assumption | H2: 1,000-vehicle sample batch used to demonstrate standard costing; not Maruti's actual production batch.
A3: Material | B3: Steel quantity | C3: 500 | D3: 510 | E3: kg/vehicle | F3: Industry-informed assumption | G3: Industry-informed modelling assumption; vehicle weight used only as contextual reference | H3: 500 kg/vehicle is an illustrative steel-equivalent assumption; Maruti does not publicly disclose model-level steel consumption.
A4: Material | B4: Steel price | C4: 55 | D4: 58 | E4: ₹/kg | F4: Benchmark + modelling assumption | G4: Government of India, Ministry of Steel / JPC steel-price data | H4: ₹55/kg used as a benchmark-informed standard input; not Maruti's actual procurement price.
A5: Material | B5: Powertrain & mechanical components | C5: 75000 | D5: 77000 | E5: ₹/vehicle | F5: Illustrative assumption | G5: Portfolio modelling assumption | H5: Public sources do not disclose Maruti's internal component procurement cost; ₹75,000 is illustrative.
A6: Material | B6: Electrical & electronic components | C6: 25000 | D6: 24000 | E6: ₹/vehicle | F6: Illustrative assumption | G6: Portfolio modelling assumption | H6: Public sources do not disclose Maruti's internal component procurement cost; ₹25,000 is illustrative.
A7: Labour | B7: Direct labour hours | C7: 15 | D7: 14.5 | E7: Hours/vehicle | F7: Illustrative assumption | G7: Portfolio modelling assumption | H7: 15 hours/vehicle represents an illustrative direct-labour standard; not a disclosed Maruti production figure.
A8: Labour | B8: Labour rate | C8: 300 | D8: 330 | E8: ₹/hour | F8: Benchmark-informed assumption | G8: Automotive-sector compensation benchmark + modelling assumption | H8: ₹300/hour is an illustrative fully loaded labour rate; not Maruti's disclosed employee cost.
A9: Overhead | B9: Variable overhead rate | C9: 125 | E9: ₹/labour hour | F9: Illustrative assumption | G9: Portfolio modelling assumption | H9: ₹125/hour used as an illustrative overhead absorption rate.
A10: Overhead | B10: Actual variable overhead | D10: 1775000 | E10: ₹/batch | F10: Illustrative assumption | G10: Portfolio modelling assumption | H10: ₹17.75 lakh represents illustrative actual expenditure for the 1,000-vehicle model.
A15: Variable | B15: Value | C15: Basis / Source | D15: Notes
A16: FY2025–26 production | B16: 2,340,000+ vehicles | C16: Maruti Suzuki India Limited — FY2025–26 production release | D16: Actual company-reported production of over 23.4 lakh vehicles.
A17: FY2025–26 total sales | B17: 2,422,713 vehicles | C17: Maruti Suzuki India Limited — FY2025–26 financial results | D17: Actual company-reported total sales of 2,422,713 vehicles.
A18: FY2025–26 net sales | B18: ₹1,743,695 million | C18: Maruti Suzuki India Limited — FY2025–26 financial results | D18: Actual company-reported net sales of ₹1,743,695 million.
A19: FY2025–26 net profit | B19: ₹144,454 million | C19: Maruti Suzuki India Limited — FY2025–26 financial results | D19: Actual company-reported net profit of ₹144,454 million.

Sheet 03 Standard Cost
A1: Cost Component | B1: Standard Quantity | C1: Standard Rate | D1: Standard Cost | E1: Cost per Vehicle
A2: Steel / Sheet Metal | B2: 500000 | C2: 55 | D2: =B2*C2 -> 27500000 | E2: =D2/1000 -> 27500
A3: Powertrain & Mechanical | B3: 1000 | C3: 75000 | D3: =B3*C3 -> 75000000 | E3: =D3/1000 -> 75000
A4: Electrical & Electronics | B4: 1000 | C4: 25000 | D4: =B4*C4 -> 25000000 | E4: =D4/1000 -> 25000
A5: Direct Labour | B5: 15000 | C5: 300 | D5: =B5*C5 -> 4500000 | E5: =D5/1000 -> 4500
A6: Variable Overhead | B6: 15000 | C6: 125 | D6: =B6*C6 -> 1875000 | E6: =D6/1000 -> 1875
A7: TOTAL | D7: =SUM(D2:D6) -> 133875000 | E7: =D7/1000 -> 133875

Sheet 04 Actual Cost
A1: Cost Component | B1: Actual Quantity | C1: Actual Rate | D1: Actual Cost | E1: Cost per Vehicle
A2: Steel / Sheet Metal | B2: 510000 | C2: 58 | D2: =B2*C2 -> 29580000 | E2: =D2/1000 -> 29580
A3: Powertrain & Mechanical | B3: 1000 | C3: 77000 | D3: =B3*C3 -> 77000000 | E3: =D3/1000 -> 77000
A4: Electrical & Electronics | B4: 1000 | C4: 24000 | D4: =B4*C4 -> 24000000 | E4: =D4/1000 -> 24000
A5: Direct Labour | B5: 14500 | C5: 330 | D5: =B5*C5 -> 4785000 | E5: =D5/1000 -> 4785
A6: Variable Overhead | B6: 14500 | C6: 125 | D6: 1775000 | E6: =D6/1000 -> 1775
A7: Total | D7: =SUM(D2:D6) -> 137140000 | E7: =SUM(E2:E6) -> 137140

Sheet 05 Material Variance
A1: Material | B1: Standard Quantity | C1: Actual Quantity | D1: Standard Rate | E1: Actual Rate | F1: Standard Cost | G1: Actual Cost | H1: Cost Variance | I1: Price Variance | J1: Usage Variance
A2: Steel / Sheet Metal | B2: 500000 | C2: 510000 | D2: 55 | E2: 58 | F2: =B2*D2 -> 27500000 | G2: =C2*E2 -> 29580000 | H2: =F2-G2 -> -2080000 | I2: =C2*(D2-E2) -> -1530000 | J2: =D2*(B2-C2) -> -550000
A3: Powertrain & Mechanical | B3: 1000 | C3: 1000 | D3: 75000 | E3: 77000 | F3: =B3*D3 -> 75000000 | G3: =C3*E3 -> 77000000 | H3: =F3-G3 -> -2000000 | I3: =C3*(D3-E3) -> -2000000 | J3: =D3*(B3-C3) -> 0
A4: Electrical & Electronics | B4: 1000 | C4: 1000 | D4: 25000 | E4: 24000 | F4: =B4*D4 -> 25000000 | G4: =C4*E4 -> 24000000 | H4: =F4-G4 -> 1000000 | I4: =C4*(D4-E4) -> 1000000 | J4: =D4*(B4-C4) -> 0
A5: TOTAL | F5: =SUM(F2:F4) -> 127500000 | G5: =SUM(G2:G4) -> 130580000 | H5: =SUM(H2:H4) -> -3080000 | I5: =SUM(I2:I4) -> -2530000 | J5: =SUM(J2:J4) -> -550000

Sheet 06 Labour Variance
A1: Labour | B1: Standard Hours | C1: Actual Hours | D1: Standard Rate | E1: Actual Rate | F1: Standard Cost | G1: Actual Cost | H1: Rate Variance | I1: Efficiency Variance | J1: Labour Cost Variance
A2: Direct Labour | B2: 15000 | C2: 14500 | D2: 300 | E2: 330 | F2: =B2*D2 -> 4500000 | G2: =C2*E2 -> 4785000 | H2: =C2*(D2-E2) -> -435000 | I2: =D2*(B2-C2) -> 150000 | J2: =F2-G2 -> -285000

Sheet 07 Overhead Variance
A1: Overhead | B1: Standard Hours | C1: Actual Hours | D1: Standard Rate | E1: Standard Overhead | F1: Actual Overhead | G1: Variance | H1: Expenditure Variance | I1: Efficiency Variance
A2: Variable Overhead | B2: 15000 | C2: 14500 | D2: 125 | E2: =B2*D2 -> 1875000 | F2: 1775000 | G2: =E2-F2 -> 100000 | H2: =(C2*D2)-F2 -> 37500 | I2: =D2*(B2-C2) -> 62500

Sheet 08 Variance Summary
A1: Cost Area | B1: Standard Cost | C1: Actual Cost | D1: Cost Variance
A2: Material | B2: ='05 Material Variance'!F5 -> 127500000 | C2: ='05 Material Variance'!G5 -> 130580000 | D2: =B2-C2 -> -3080000
A3: Direct Labour | B3: {=Table7[Standard Cost]} -> 4500000 | C3: {=Table7[Actual Cost]} -> 4785000 | D3: =B3-C3 -> -285000
A4: Variable Overhead | B4: {=Table4[Standard Overhead]} -> 1875000 | C4: {=Table4[Actual Overhead]} -> 1775000 | D4: =B4-C4 -> 100000
A5: Total | B5: =SUM(B2:B4) -> 133875000 | C5: =SUM(C2:C4) -> 137140000 | D5: =B5-C5 -> -3265000
A9: Variance Type | B9: Amount | C9: Result
A10: Material Variance | B10: =ABS(D2) -> 3080000 | C10: Adverse
A11: Labour Variance | B11: =ABS(D3) -> 285000 | C11: Adverse
A12: Overhead Variance | B12: =D4 -> 100000 | C12: Favourable
A13: Overall Variance | B13: =ABS(D5) -> 3265000 | C13: Adverse
A16: RECONCILIATION CHECK | B16: Result
A17: Standard Cost | B17: =B5 -> 133875000
A18: Actual Cost | B18: =C5 -> 137140000
A19: Difference | B19: =B17-B18 -> -3265000
A20: Absolute Variance | B20: =ABS(B19) -> 3265000
A21: Reconciliation Status | B21: =IF(B20=3265000,"CHECK PASSED","CHECK FAILED") -> CHECK PASSED

Sheet 09 Dashboard
A1: STANDARD COSTING & VARIANCE ANALYSIS DASHBOARD
A2: Illustrative Automobile Manufacturing Case Study — FY 2025–26
A4: Standard Cost | C4: Actual Cost | E4: Overall Variance | G4: Variance / Vehicle
A5: ='08 Variance Summary'!B5 -> 133875000 | C5: ='08 Variance Summary'!C5 -> 137140000 | E5: =ABS('08 Variance Summary'!D5) -> 3265000 | G5: =ABS(E5)/1000 -> 3265
E6: ADVERSE | G6: ADVERSE
A8: Cost Area | B8: Standard Cost | C8: Actual Cost | E8: Cost Area | F8: Variance | G8: Status
A9: Material | B9: ='08 Variance Summary'!B2 -> 127500000 | C9: ='08 Variance Summary'!C2 -> 130580000 | E9: Material | F9: ='08 Variance Summary'!D2 -> -3080000 | G9: Adverse
A10: Direct Labour | B10: ='08 Variance Summary'!B3 -> 4500000 | C10: ='08 Variance Summary'!C3 -> 4785000 | E10: Labour | F10: ='08 Variance Summary'!D3 -> -285000 | G10: Adverse
A11: Variable Overhead | B11: ='08 Variance Summary'!B4 -> 1875000 | C11: ='08 Variance Summary'!C4 -> 1775000 | E11: Overhead | F11: ='08 Variance Summary'!D4 -> 100000 | G11: Favourable
A29: Key Findings
A30: 1. Material costs generated the largest adverse variance of ₹30.80 lakh.
A31: 2. Labour efficiency was favourable by ₹1.50 lakh, but the higher labour rate created a ₹4.35 lakh adverse rate variance.
A32: 3. Variable overhead was ₹1.00 lakh favourable.
A33: 4. Overall actual cost exceeded standard cost by ₹32.65 lakh, equivalent to ₹3,265 per vehicle.
A36: Note: Company information is based on publicly available Maruti Suzuki information. Detailed standard and actual cost inputs are illustrative modelling assumptions developed for portfolio/educational purposes and do not represent confidential Maruti Suzuki internal cost data.
